bps_searcher/__init__.py
bps_searcher/__main__.py
bps_searcher/bps_api_client.py
bps_searcher/bps_mcp_server.py
bps_searcher/main.py
bps_searcher/resources/hs-code/HSCode Master BPS.pdf
bps_searcher-0.1.4.dist-info/METADATA
bps_searcher-0.1.4.dist-info/WHEEL
bps_searcher-0.1.4.dist-info/entry_points.txt
bps_searcher-0.1.4.dist-info/top_level.txt
bps_searcher-0.1.4.dist-info/RECORD
