Metadata-Version: 2.4
Name: bps-searcher
Version: 0.1.4
Summary: BPS搜索MCP工具 - 用于查询印尼相关数据
Requires-Python: >=3.10
Requires-Dist: fastmcp>=2.11.2
Requires-Dist: pytest>=8.4.1
Requires-Dist: pytest-asyncio>=0.21.0
Requires-Dist: requests>=2.31.0
Requires-Dist: PyMuPDF>=1.18.0
Requires-Dist: setuptools>=45
